python_library/__init__.py
python_library/sample.py
tests/__init__.py
tests/integration/__init__.py
tests/integration/test_mongo_connection.py
tests/integration/test_neo4j_connection.py
tests/integration/test_rabbitmq_connection.py
python_lib_template-1.0.0.dist-info/METADATA
python_lib_template-1.0.0.dist-info/WHEEL
python_lib_template-1.0.0.dist-info/top_level.txt
python_lib_template-1.0.0.dist-info/RECORD
